[
  {
    "text": "Bündnis gegen Verdrängung und",
    "bbox": [
      [
        297.0,
        23.0
      ],
      [
        725.0,
        23.0
      ],
      [
        725.0,
        92.0
      ],
      [
        297.0,
        92.0
      ]
    ],
    "confidence": 0.9967452705355578
  },
  {
    "text": "00",
    "bbox": [
      [
        761.0,
        83.0
      ],
      [
        791.0,
        83.0
      ],
      [
        791.0,
        99.0
      ],
      [
        761.0,
        99.0
      ]
    ],
    "confidence": 0.8924319958556639
  },
  {
    "text": "00",
    "bbox": [
      [
        761.0,
        99.0
      ],
      [
        791.0,
        99.0
      ],
      [
        791.0,
        115.0
      ],
      [
        761.0,
        115.0
      ]
    ],
    "confidence": 0.9598821537884175
  },
  {
    "text": "#Mietenwahnsinn",
    "bbox": [
      [
        301.0,
        74.0
      ],
      [
        731.0,
        74.0
      ],
      [
        731.0,
        163.0
      ],
      [
        301.0,
        163.0
      ]
    ],
    "confidence": 0.9994036863502945
  },
  {
    "text": "0 0",
    "bbox": [
      [
        761.0,
        117.0
      ],
      [
        791.0,
        117.0
      ],
      [
        791.0,
        135.0
      ],
      [
        761.0,
        135.0
      ]
    ],
    "confidence": 0.8910928346999116
  },
  {
    "text": "0 0",
    "bbox": [
      [
        761.0,
        135.0
      ],
      [
        789.0,
        135.0
      ],
      [
        789.0,
        153.0
      ],
      [
        761.0,
        153.0
      ]
    ],
    "confidence": 0.6833796819576999
  },
  {
    "text": "0 0",
    "bbox": [
      [
        761.0,
        155.0
      ],
      [
        791.0,
        155.0
      ],
      [
        791.0,
        171.0
      ],
      [
        761.0,
        171.0
      ]
    ],
    "confidence": 0.9475545217002637
  },
  {
    "text": "www.mietenwahnsinninfo",
    "bbox": [
      [
        305.0,
        151.0
      ],
      [
        719.0,
        151.0
      ],
      [
        719.0,
        191.0
      ],
      [
        305.0,
        191.0
      ]
    ],
    "confidence": 0.9878732880721159
  },
  {
    "text": "DIE MIETE",
    "bbox": [
      [
        191.0,
        195.0
      ],
      [
        837.0,
        195.0
      ],
      [
        837.0,
        405.0
      ],
      [
        191.0,
        405.0
      ]
    ],
    "confidence": 0.9966657964194816
  },
  {
    "text": "0 0",
    "bbox": [
      [
        111.0,
        451.0
      ],
      [
        143.0,
        451.0
      ],
      [
        143.0,
        469.0
      ],
      [
        111.0,
        469.0
      ]
    ],
    "confidence": 0.8938968181610107
  },
  {
    "text": "00",
    "bbox": [
      [
        111.0,
        469.0
      ],
      [
        143.0,
        469.0
      ],
      [
        143.0,
        489.0
      ],
      [
        111.0,
        489.0
      ]
    ],
    "confidence": 0.872663608188436
  },
  {
    "text": "0",
    "bbox": [
      [
        85.0,
        486.0
      ],
      [
        104.0,
        486.0
      ],
      [
        104.0,
        527.0
      ],
      [
        85.0,
        527.0
      ]
    ],
    "confidence": 0.6034881203604527
  },
  {
    "text": "IST ZU",
    "bbox": [
      [
        300.0,
        412.0
      ],
      [
        716.0,
        412.0
      ],
      [
        716.0,
        608.0
      ],
      [
        300.0,
        608.0
      ]
    ],
    "confidence": 0.7086523837803606
  },
  {
    "text": "HOCH!",
    "bbox": [
      [
        306.0,
        608.0
      ],
      [
        732.0,
        608.0
      ],
      [
        732.0,
        829.0
      ],
      [
        306.0,
        829.0
      ]
    ],
    "confidence": 0.9855963920134052
  },
  {
    "text": "Demo; Samstag 01.Juni 2024",
    "bbox": [
      [
        168.0,
        829.0
      ],
      [
        854.0,
        829.0
      ],
      [
        854.0,
        934.0
      ],
      [
        168.0,
        934.0
      ]
    ],
    "confidence": 0.9513798771415058
  },
  {
    "text": "14.00 Uhr Potsdamer Platz",
    "bbox": [
      [
        191.0,
        917.0
      ],
      [
        809.0,
        917.0
      ],
      [
        809.0,
        1003.0
      ],
      [
        191.0,
        1003.0
      ]
    ],
    "confidence": 0.9396869398883242
  },
  {
    "text": "und",
    "bbox": [
      [
        662.6263943605131,
        31.192380261795883
      ],
      [
        722.6069366051547,
        25.537340859051433
      ],
      [
        724.3736056394869,
        75.80761973820411
      ],
      [
        665.3930633948453,
        80.46265914094857
      ]
    ],
    "confidence": 0.9962050324714012
  },
  {
    "text": "0",
    "bbox": [
      [
        87.0,
        509.0
      ],
      [
        101.0,
        509.0
      ],
      [
        101.0,
        547.0
      ],
      [
        87.0,
        547.0
      ]
    ],
    "confidence": 0.9502317680358061
  },
  {
    "text": "0o",
    "bbox": [
      [
        111.0,
        491.0
      ],
      [
        143.0,
        491.0
      ],
      [
        143.0,
        509.0
      ],
      [
        111.0,
        509.0
      ]
    ],
    "confidence": 0.2893140181044073
  },
  {
    "text": "2",
    "bbox": [
      [
        921.0,
        501.0
      ],
      [
        960.0,
        501.0
      ],
      [
        960.0,
        588.0
      ],
      [
        921.0,
        588.0
      ]
    ],
    "confidence": 0.0209581102487002
  },
  {
    "text": "WWWV",
    "bbox": [
      [
        308.0,
        160.0
      ],
      [
        390.0,
        160.0
      ],
      [
        390.0,
        186.0
      ],
      [
        308.0,
        186.0
      ]
    ],
    "confidence": 0.35914498567581177
  },
  {
    "text": "'t",
    "bbox": [
      [
        693.0,
        925.0
      ],
      [
        805.0,
        925.0
      ],
      [
        805.0,
        985.0
      ],
      [
        693.0,
        985.0
      ]
    ],
    "confidence": 0.5418778909958482
  }
]