[
  {
    "text": "KinderUni Lichtenberg",
    "bbox": [
      [
        57.0,
        88.0
      ],
      [
        868.0,
        88.0
      ],
      [
        868.0,
        185.0
      ],
      [
        57.0,
        185.0
      ]
    ],
    "confidence": 0.9992995236446456
  },
  {
    "text": "Wie kann man in den",
    "bbox": [
      [
        62.0,
        200.0
      ],
      [
        688.0,
        200.0
      ],
      [
        688.0,
        274.0
      ],
      [
        62.0,
        274.0
      ]
    ],
    "confidence": 0.9932521404292561
  },
  {
    "text": "Kopf schauen?",
    "bbox": [
      [
        61.0,
        266.0
      ],
      [
        497.0,
        266.0
      ],
      [
        497.0,
        352.0
      ],
      [
        61.0,
        352.0
      ]
    ],
    "confidence": 0.9999723592693194
  },
  {
    "text": "Prof. Dr. Annabella",
    "bbox": [
      [
        63.0,
        322.0
      ],
      [
        628.0,
        322.0
      ],
      [
        628.0,
        406.0
      ],
      [
        63.0,
        406.0
      ]
    ],
    "confidence": 0.9074328936486019
  },
  {
    "text": "Rauscher-Scheibe, HTW Berlin",
    "bbox": [
      [
        67.0,
        384.0
      ],
      [
        954.0,
        384.0
      ],
      [
        954.0,
        465.0
      ],
      [
        67.0,
        465.0
      ]
    ],
    "confidence": 0.9600673044521529
  },
  {
    "text": "10.30 Uhr",
    "bbox": [
      [
        246.0,
        456.0
      ],
      [
        530.0,
        456.0
      ],
      [
        530.0,
        531.0
      ],
      [
        246.0,
        531.0
      ]
    ],
    "confidence": 0.9103171197729989
  },
  {
    "text": "9.11.",
    "bbox": [
      [
        65.0,
        470.0
      ],
      [
        204.0,
        470.0
      ],
      [
        204.0,
        532.0
      ],
      [
        65.0,
        532.0
      ]
    ],
    "confidence": 0.9975578508532947
  },
  {
    "text": "1",
    "bbox": [
      [
        217.0,
        473.0
      ],
      [
        237.0,
        473.0
      ],
      [
        237.0,
        513.0
      ],
      [
        217.0,
        513.0
      ]
    ],
    "confidence": 0.3096881565720402
  },
  {
    "text": "0",
    "bbox": [
      [
        511.0,
        521.0
      ],
      [
        709.0,
        521.0
      ],
      [
        709.0,
        684.0
      ],
      [
        511.0,
        684.0
      ]
    ],
    "confidence": 0.9927895577904202
  },
  {
    "text": "20",
    "bbox": [
      [
        464.0,
        524.0
      ],
      [
        708.0,
        524.0
      ],
      [
        708.0,
        700.0
      ],
      [
        464.0,
        700.0
      ]
    ],
    "confidence": 0.33043797621893384
  }
]