[
  {
    "text": "RAUS",
    "bbox": [
      [
        955.0,
        39.0
      ],
      [
        1049.0,
        39.0
      ],
      [
        1049.0,
        75.0
      ],
      [
        955.0,
        75.0
      ]
    ],
    "confidence": 0.999289333820343
  },
  {
    "text": "GEGA",
    "bbox": [
      [
        955.0,
        69.0
      ],
      [
        1049.0,
        69.0
      ],
      [
        1049.0,
        105.0
      ],
      [
        955.0,
        105.0
      ]
    ],
    "confidence": 0.9999068379402161
  },
  {
    "text": "NGEN",
    "bbox": [
      [
        957.0,
        99.0
      ],
      [
        1051.0,
        99.0
      ],
      [
        1051.0,
        135.0
      ],
      [
        957.0,
        135.0
      ]
    ],
    "confidence": 0.9968639612197876
  },
  {
    "text": "1",
    "bbox": [
      [
        836.0,
        546.0
      ],
      [
        976.0,
        546.0
      ],
      [
        976.0,
        596.0
      ],
      [
        836.0,
        596.0
      ]
    ],
    "confidence": 0.1166246207980004
  },
  {
    "text": "EROBIQUE",
    "bbox": [
      [
        109.0,
        725.0
      ],
      [
        518.0,
        725.0
      ],
      [
        518.0,
        805.0
      ],
      [
        109.0,
        805.0
      ]
    ],
    "confidence": 0.9998320811156026
  },
  {
    "text": "NEUJAHRS PARTY",
    "bbox": [
      [
        111.0,
        791.0
      ],
      [
        804.0,
        791.0
      ],
      [
        804.0,
        859.0
      ],
      [
        111.0,
        859.0
      ]
    ],
    "confidence": 0.9955140372779917
  },
  {
    "text": "P",
    "bbox": [
      [
        978.0,
        700.0
      ],
      [
        1080.0,
        700.0
      ],
      [
        1080.0,
        1005.0
      ],
      [
        978.0,
        1005.0
      ]
    ],
    "confidence": 0.909154355227443
  },
  {
    "text": "FESTSAAL KREUZBERG",
    "bbox": [
      [
        112.0,
        882.0
      ],
      [
        702.0,
        882.0
      ],
      [
        702.0,
        932.0
      ],
      [
        112.0,
        932.0
      ]
    ],
    "confidence": 0.9996837582722203
  },
  {
    "text": "01.01. AB 21:00 UHR",
    "bbox": [
      [
        194.0,
        958.0
      ],
      [
        689.0,
        958.0
      ],
      [
        689.0,
        1006.0
      ],
      [
        194.0,
        1006.0
      ]
    ],
    "confidence": 0.9183782129496747
  },
  {
    "text": "l",
    "bbox": [
      [
        751.4468107366356,
        -27.9744440443357
      ],
      [
        969.9808916712168,
        39.52152866630266
      ],
      [
        950.5531892633644,
        91.9744440443357
      ],
      [
        733.0191083287832,
        22.47847133369734
      ]
    ],
    "confidence": 0.1742472189644042
  },
  {
    "text": "ETAGE",
    "bbox": [
      [
        736.3765016118952,
        23.02162321129088
      ],
      [
        970.9509438219641,
        116.06159459931023
      ],
      [
        940.6234983881048,
        184.9783767887091
      ],
      [
        705.0490561780359,
        91.93840540068977
      ]
    ],
    "confidence": 0.6195401014940635
  },
  {
    "text": "1",
    "bbox": [
      [
        948.101167723432,
        120.0677069746514
      ],
      [
        1045.8985383186287,
        147.9012526661378
      ],
      [
        1029.8988322765679,
        197.9322930253486
      ],
      [
        932.1014616813713,
        169.0987473338622
      ]
    ],
    "confidence": 0.17016696514666396
  },
  {
    "text": "1 '",
    "bbox": [
      [
        750.4652322401421,
        110.01590163438665
      ],
      [
        1044.9012733094305,
        224.67058905118893
      ],
      [
        1013.5347677598579,
        295.98409836561336
      ],
      [
        719.0987266905694,
        181.32941094881107
      ]
    ],
    "confidence": 0.3509334325790405
  },
  {
    "text": "1",
    "bbox": [
      [
        768.493038515975,
        187.01285876470573
      ],
      [
        1038.7555624845663,
        326.80250128334
      ],
      [
        996.506961484025,
        403.98714123529425
      ],
      [
        726.2444375154337,
        265.19749871666
      ]
    ],
    "confidence": 0.31159502745225964
  },
  {
    "text": "1",
    "bbox": [
      [
        750.4278588239114,
        281.01488941909895
      ],
      [
        1027.8820210526756,
        408.3932586365177
      ],
      [
        985.5721411760886,
        494.98511058090105
      ],
      [
        708.1179789473244,
        367.6067413634823
      ]
    ],
    "confidence": 0.38025125006740623
  },
  {
    "text": "1",
    "bbox": [
      [
        746.1752602674111,
        404.030961556568
      ],
      [
        1025.9803456507939,
        472.3427257885088
      ],
      [
        999.8247397325889,
        558.969038443432
      ],
      [
        720.0196543492061,
        490.6572742114912
      ]
    ],
    "confidence": 0.5172484902032579
  },
  {
    "text": "MI",
    "bbox": [
      [
        112.0,
        958.0
      ],
      [
        180.0,
        958.0
      ],
      [
        180.0,
        1006.0
      ],
      [
        112.0,
        1006.0
      ]
    ],
    "confidence": 0.9991913820601734
  },
  {
    "text": "1",
    "bbox": [
      [
        1034.0,
        0.0
      ],
      [
        1078.0,
        0.0
      ],
      [
        1078.0,
        22.0
      ],
      [
        1034.0,
        22.0
      ]
    ],
    "confidence": 0.0552984212664962
  },
  {
    "text": "1 ",
    "bbox": [
      [
        738.118489277029,
        496.03892883042755
      ],
      [
        1029.9363134656955,
        544.8732015657458
      ],
      [
        1010.881510722971,
        628.9610711695724
      ],
      [
        719.0636865343045,
        580.1267984342542
      ]
    ],
    "confidence": 0.3634757995605469
  },
  {
    "text": "1",
    "bbox": [
      [
        862.0,
        624.0
      ],
      [
        964.0,
        624.0
      ],
      [
        964.0,
        672.0
      ],
      [
        862.0,
        672.0
      ]
    ],
    "confidence": 0.045255266109567316
  },
  {
    "text": "01.01.",
    "bbox": [
      [
        196.0,
        958.0
      ],
      [
        334.0,
        958.0
      ],
      [
        334.0,
        1006.0
      ],
      [
        196.0,
        1006.0
      ]
    ],
    "confidence": 0.9831591907740029
  },
  {
    "text": "1 _",
    "bbox": [
      [
        795.0,
        615.0
      ],
      [
        1021.0,
        615.0
      ],
      [
        1021.0,
        677.0
      ],
      [
        795.0,
        677.0
      ]
    ],
    "confidence": 0.054987625969802834
  },
  {
    "text": "MI, 01.01.",
    "bbox": [
      [
        108.0,
        954.0
      ],
      [
        335.0,
        954.0
      ],
      [
        335.0,
        1014.0
      ],
      [
        108.0,
        1014.0
      ]
    ],
    "confidence": 0.9587362061934888
  },
  {
    "text": "48q4C2",
    "bbox": [
      [
        346.0,
        958.0
      ],
      [
        566.0,
        958.0
      ],
      [
        566.0,
        1006.0
      ],
      [
        346.0,
        1006.0
      ]
    ],
    "confidence": 0.1387866098055746
  }
]